{
  "team": {
    "name": "Never Give Up",
    "slug": "Never_Give_Up",
    "short_name": "NGU",
    "emoji": "🇻🇳",
    "game": "leagueoflegends",
    "liquipedia_url": "https://liquipedia.net/leagueoflegends/Never_Give_Up"
  },
  "matches": [
    {
      "timestamp": 1752919200,
      "opponent": "Saigon Dino",
      "tournament": "VCS Finals",
      "url": "https://liquipedia.net/leagueoflegends/VCS/2025/Finals#Results",
      "is_upcoming": false
    },
    {
      "timestamp": 1749895200,
      "opponent": "Saigon Dino",
      "tournament": "VCS Summer - Playoffs Results",
      "url": "https://liquipedia.net/leagueoflegends/VCS/2025/Summer/Playoffs#Playoffs_Results",
      "is_upcoming": false
    },
    {
      "timestamp": 1749722400,
      "opponent": "CyberCore Esports",
      "tournament": "VCS Summer - Playoffs Results",
      "url": "https://liquipedia.net/leagueoflegends/VCS/2025/Summer/Playoffs#Playoffs_Results",
      "is_upcoming": false
    },
    {
      "timestamp": 1748944800,
      "opponent": "CyberCore Esports",
      "tournament": "VCS Summer - Round 3",
      "url": "https://liquipedia.net/leagueoflegends/VCS/2025/Summer/Swiss_Stage#Round_3",
      "is_upcoming": false
    },
    {
      "timestamp": 1748512800,
      "opponent": "Mila Gaming",
      "tournament": "VCS Summer - Round 2",
      "url": "https://liquipedia.net/leagueoflegends/VCS/2025/Summer/Swiss_Stage#Round_2",
      "is_upcoming": false
    },
    {
      "timestamp": 1748346000,
      "opponent": "Vikings Esports Academy",
      "tournament": "VCS Summer - Round 1",
      "url": "https://liquipedia.net/leagueoflegends/VCS/2025/Summer/Swiss_Stage#Round_1",
      "is_upcoming": false
    },
    {
      "timestamp": 1746957600,
      "opponent": "Venus Gaming",
      "tournament": "VCS Summer Promotion",
      "url": "https://liquipedia.net/leagueoflegends/VCS/2025/Summer/Promotion#Results",
      "is_upcoming": false
    },
    {
      "timestamp": 1746871200,
      "opponent": "GenZ Gaming",
      "tournament": "VCS Summer Promotion",
      "url": "https://liquipedia.net/leagueoflegends/VCS/2025/Summer/Promotion#Results",
      "is_upcoming": false
    },
    {
      "timestamp": 1746777600,
      "opponent": "HST Team Esports",
      "tournament": "VCS Summer Promotion",
      "url": "https://liquipedia.net/leagueoflegends/VCS/2025/Summer/Promotion#Results",
      "is_upcoming": false
    },
    {
      "timestamp": 1746698400,
      "opponent": "Evil Genius",
      "tournament": "VCS Summer Promotion",
      "url": "https://liquipedia.net/leagueoflegends/VCS/2025/Summer/Promotion#Results",
      "is_upcoming": false
    }
  ],
  "generated_utc": "2026-01-28T15:40:59Z"
}